{
  "userInfo": [
    {
      "id": "fsync_13",
      "password": "Alpha123!!"
    },
    {
      "id": "Amit",
      "password": "12345"
    },
    {
      "id": "Shreya",
      "password": "Alpha"
    },
    {
      "id": "Vee",
      "password": "@Shradz"
    },
    {
      "id": "fsync_13",
      "password": "Alpha123"
    },
    {
      "id": "12345",
      "password": "xyz"
    },
    {
      "userInfo": [
        {
          "id": "fsync_13",
          "password": "Alpha123!!"
        },
        {
          "id": "Amit",
          "password": "12345"
        },
        {
          "id": "Shreya",
          "password": "Alpha"
        },
        {
          "id": "Vee",
          "password": "@Shradz"
        },
        {
          "id": "fsync_13",
          "password": "Alpha123"
        },
        {
          "id": "12345",
          "password": "xyz"
        }
      ],
      "id": "_U0SkUP"
    }
  ]
}